gstoolspy
