Metadata-Version: 2.1
Name: gstoolspy
Version: 2.2.4
Summary: GsTools é uma ferramenta poderosa para disponibilizar dados de abas do Google Sheets. Com uma configuração simples e suporte a múltiplas abas, o GSTools facilita a integração de dados do Google Sheets em seus projetos Python.
Home-page: https://github.com/hqr90/gsTools
Author: Hilton Queiroz Rebello
Author-email: rebello.hiltonqueiroz@gmail.com
Classifier: Programming Language :: Python :: 3
Classifier: License :: OSI Approved :: MIT License
Classifier: Operating System :: OS Independent
Requires-Python: >=3.6
License-File: LICENSE
Requires-Dist: gspread
